whichlang_py-0.1.0.dist-info/METADATA
whichlang_py-0.1.0.dist-info/WHEEL
whichlang_py-0.1.0.dist-info/license_files/LICENSE
whichlang_py/__init__.py
whichlang_py/whichlang_py.cp310-win32.pyd
whichlang_py-0.1.0.dist-info/RECORD
